jcs/__init__.py
jcs/_jcs.py
jcs/ntoj.py
jcs-0.2.0.dist-info/WHEEL
jcs-0.2.0.dist-info/METADATA
jcs-0.2.0.dist-info/RECORD
