Metadata-Version: 2.1
Name: jcs
Version: 0.2.0
Summary: JSC - JSON Canonicalization
Home-page: https://github.com/titusz/jcs
License: Apache-2.0
Keywords: jcs,json,canonicalization,deterministic,serialization,hash
Author: titusz
Author-email: tp@py7.de
Requires-Python: >=3.6
Classifier: License :: OSI Approved :: Apache Software License
Classifier: Programming Language :: Python :: 3
Classifier: Programming Language :: Python :: 3.10
Classifier: Programming Language :: Python :: 3.6
Classifier: Programming Language :: Python :: 3.7
Classifier: Programming Language :: Python :: 3.8
Classifier: Programming Language :: Python :: 3.9
Project-URL: Repository, https://github.com/titusz/jcs
